generate_pdf.py
rudolf_st_hw_2_latex_gen-1.0.0.dist-info/METADATA
rudolf_st_hw_2_latex_gen-1.0.0.dist-info/WHEEL
rudolf_st_hw_2_latex_gen-1.0.0.dist-info/top_level.txt
rudolf_st_hw_2_latex_gen-1.0.0.dist-info/RECORD
