Metadata-Version: 2.2
Name: rudolf_st_hw_2_latex_gen
Version: 1.0.0
Summary: For homeworks
Requires-Python: >=3.13
Requires-Dist: click>=8.1.8
Requires-Dist: pdflatex>=0.1.3
Requires-Dist: setuptools>=76.0.0
